statlink/__init__.py
statlink/command.py
statlink/crawler.py
statlink/engine.py
statlink/filter.py
statlink/node.py
statlink/output.py
statlink/request.py
statlink/response.py
statlink/source.py
statlink/store.py
statlink/utils.py
statlink-0.1.6.dist-info/entry_points.txt
statlink-0.1.6.dist-info/LICENSE
statlink-0.1.6.dist-info/WHEEL
statlink-0.1.6.dist-info/METADATA
statlink-0.1.6.dist-info/RECORD
