Metadata-Version: 2.1
Name: statlink
Version: 0.1.6
Summary: An asyncio based multipurpose link checker.
Author: Thibaut Frain
Author-email: thibaut.frain@gmail.com
Requires-Python: >=3.7,<4.0
Classifier: Programming Language :: Python :: 3
Classifier: Programming Language :: Python :: 3.7
Classifier: Programming Language :: Python :: 3.8
Classifier: Programming Language :: Python :: 3.9
Classifier: Programming Language :: Python :: 3.10
Classifier: Programming Language :: Python :: 3.11
Requires-Dist: aiohttp (>=3.8.1,<4.0.0)
Requires-Dist: aiolimiter (>=1.0.0,<2.0.0)
Requires-Dist: click (>=8.1.3,<9.0.0)
Requires-Dist: lxml (>=4.9.1,<5.0.0)
Requires-Dist: playwright (>=1.28.0,<2.0.0)
Requires-Dist: rich (>=12.5.1,<13.0.0)
